p2pool_api/__init__.py
p2pool_api/p2pool.py
p2pool_api-0.0.3.dist-info/METADATA
p2pool_api-0.0.3.dist-info/WHEEL
p2pool_api-0.0.3.dist-info/licenses/LICENSE
p2pool_api-0.0.3.dist-info/RECORD
