Metadata-Version: 2.3
Name: p2pool-api
Version: 0.0.3
Summary: Allows interacting with the P2Pool API.
Project-URL: Homepage, https://github.com/hreikin/p2pool-api
Project-URL: Issues, https://github.com/hreikin/p2pool-api/issues
Author-email: hreikin <hreikin@gmail.com>
Classifier: License :: OSI Approved :: MIT License
Classifier: Operating System :: OS Independent
Classifier: Programming Language :: Python :: 3
Requires-Python: >=3.8
Requires-Dist: mkdocs-material
Requires-Dist: mkdocstrings[python]
